emojipedia_search/__init__.py
emojipedia_search/__main__.py
emojipedia_search-0.0.2.dist-info/AUTHORS
emojipedia_search-0.0.2.dist-info/LICENSE
emojipedia_search-0.0.2.dist-info/METADATA
emojipedia_search-0.0.2.dist-info/WHEEL
emojipedia_search-0.0.2.dist-info/entry_points.txt
emojipedia_search-0.0.2.dist-info/top_level.txt
emojipedia_search-0.0.2.dist-info/RECORD
