Metadata-Version: 2.1
Name: emojipedia-search
Version: 0.0.2
Summary: TODO
Home-page: https://gitlab.com/nul.one/emojipedia_search
Author: Predrag Mandic
Author-email: predrag@nul.one
License: BSD
Download-URL: https://gitlab.com/nul.one/emojipedia_search/-/archive/0.0.2/emojipedia_search-0.0.2.tar.gz
Platform: UNKNOWN
Classifier: Development Status :: 4 - Beta
Classifier: Environment :: Console
Classifier: License :: OSI Approved :: BSD License
Classifier: Natural Language :: English
Classifier: Operating System :: POSIX :: Linux
Classifier: Programming Language :: Python :: 3 :: Only
Classifier: Topic :: Utilities
Requires-Python: >=3.4.6
Requires-Dist: beautifulsoup4 (<5.0,>=4.4.1)
Requires-Dist: requests (<3.0,>=2.18.4)
Requires-Dist: clipboard (==0.0.4)
